sms/__init__.py
sms/config.py
softlink-0.1.5.dist-info/LICENSE
softlink-0.1.5.dist-info/METADATA
softlink-0.1.5.dist-info/WHEEL
softlink-0.1.5.dist-info/RECORD
